{
  "anime": {
    "genres": [
      {
        "genre": "Drama",
        "count": 210,
        "meanScore": 78.9,
        "minutesWatched": 117385
      },
      {
        "genre": "Comedy",
        "count": 206,
        "meanScore": 73.36,
        "minutesWatched": 96026
      },
      {
        "genre": "Romance",
        "count": 221,
        "meanScore": 71.48,
        "minutesWatched": 75810
      },
      {
        "genre": "Action",
        "count": 145,
        "meanScore": 79.19,
        "minutesWatched": 91964
      },
      {
        "genre": "Fantasy",
        "count": 142,
        "meanScore": 76.8,
        "minutesWatched": 80158
      },
      {
        "genre": "Adventure",
        "count": 110,
        "meanScore": 77.67,
        "minutesWatched": 73364
      },
      {
        "genre": "Slice of Life",
        "count": 141,
        "meanScore": 75.04,
        "minutesWatched": 57177
      },
      {
        "genre": "Supernatural",
        "count": 99,
        "meanScore": 80.14,
        "minutesWatched": 62567
      },
      {
        "genre": "Psychological",
        "count": 50,
        "meanScore": 85.9,
        "minutesWatched": 23690
      },
      {
        "genre": "Mystery",
        "count": 35,
        "meanScore": 85.54,
        "minutesWatched": 21978
      },
      {
        "genre": "Sci-Fi",
        "count": 42,
        "meanScore": 82.18,
        "minutesWatched": 15710
      },
      {
        "genre": "Thriller",
        "count": 16,
        "meanScore": 90.33,
        "minutesWatched": 10369
      },
      {
        "genre": "Ecchi",
        "count": 26,
        "meanScore": 74.15,
        "minutesWatched": 13786
      },
      {
        "genre": "Mecha",
        "count": 4,
        "meanScore": 99,
        "minutesWatched": 1032
      },
      {
        "genre": "Sports",
        "count": 8,
        "meanScore": 79.6,
        "minutesWatched": 3183
      },
      {
        "genre": "Music",
        "count": 6,
        "meanScore": 81.75,
        "minutesWatched": 1401
      },
      {
        "genre": "Horror",
        "count": 10,
        "meanScore": 72.25,
        "minutesWatched": 2765
      },
      {
        "genre": "Mahou Shoujo",
        "count": 2,
        "meanScore": 50,
        "minutesWatched": 266
      }
    ]
  },
  "manga": {
    "genres": [
      {
        "genre": "Romance",
        "count": 14,
        "meanScore": 81.43,
        "chaptersRead": 487
      },
      {
        "genre": "Drama",
        "count": 11,
        "meanScore": 86,
        "chaptersRead": 344
      },
      {
        "genre": "Slice of Life",
        "count": 5,
        "meanScore": 76.67,
        "chaptersRead": 319
      },
      {
        "genre": "Comedy",
        "count": 5,
        "meanScore": 70,
        "chaptersRead": 216
      },
      {
        "genre": "Psychological",
        "count": 6,
        "meanScore": 93.33,
        "chaptersRead": 57
      },
      {
        "genre": "Supernatural",
        "count": 2,
        "meanScore": 100,
        "chaptersRead": 19
      },
      {
        "genre": "Adventure",
        "count": 2,
        "meanScore": 0,
        "chaptersRead": 7
      },
      {
        "genre": "Fantasy",
        "count": 2,
        "meanScore": 0,
        "chaptersRead": 3
      },
      {
        "genre": "Ecchi",
        "count": 1,
        "meanScore": 0,
        "chaptersRead": 2
      },
      {
        "genre": "Horror",
        "count": 1,
        "meanScore": 0,
        "chaptersRead": 1
      }
    ]
  }
}